FortuneData/__init__.py
FortuneData/database.py
FortuneData/datasource.py
FortuneData-1.0.4.dist-info/METADATA
FortuneData-1.0.4.dist-info/WHEEL
FortuneData-1.0.4.dist-info/top_level.txt
FortuneData-1.0.4.dist-info/RECORD
