Metadata-Version: 2.1
Name: FortuneData
Version: 1.0.4
Summary: 从Fortune网站获取世界500强数据
Home-page: UNKNOWN
Author: puwow
Author-email: qiaoguosong@sina.com.cn
License: MIT
Platform: UNKNOWN
Classifier: License :: OSI Approved :: MIT License
Classifier: Programming Language :: Python :: 3
Requires-Dist: peewee
Requires-Dist: requests
Requires-Dist: bs4
